six.py
six-1.7.1.dist-info/METADATA
six-1.7.1.dist-info/top_level.txt
six-1.7.1.dist-info/DESCRIPTION.rst
six-1.7.1.dist-info/metadata.json
six-1.7.1.dist-info/RECORD
six-1.7.1.dist-info/WHEEL
